IPython/__init__.py
IPython/__main__.py
IPython/conftest.py
IPython/consoleapp.py
IPython/display.py
IPython/paths.py
IPython/py.typed
IPython/core/__init__.py
IPython/core/alias.py
IPython/core/application.py
IPython/core/async_helpers.py
IPython/core/autocall.py
IPython/core/builtin_trap.py
IPython/core/compilerop.py
IPython/core/completer.py
IPython/core/completerlib.py
IPython/core/crashhandler.py
IPython/core/debugger.py
IPython/core/display.py
IPython/core/display_functions.py
IPython/core/display_trap.py
IPython/core/displayhook.py
IPython/core/displaypub.py
IPython/core/error.py
IPython/core/events.py
IPython/core/excolors.py
IPython/core/extensions.py
IPython/core/formatters.py
IPython/core/getipython.py
IPython/core/guarded_eval.py
IPython/core/history.py
IPython/core/historyapp.py
IPython/core/hooks.py
IPython/core/inputsplitter.py
IPython/core/inputtransformer.py
IPython/core/inputtransformer2.py
IPython/core/interactiveshell.py
IPython/core/latex_symbols.py
IPython/core/logger.py
IPython/core/macro.py
IPython/core/magic.py
IPython/core/magic_arguments.py
IPython/core/oinspect.py
IPython/core/page.py
IPython/core/payload.py
IPython/core/payloadpage.py
IPython/core/prefilter.py
IPython/core/profileapp.py
IPython/core/profiledir.py
IPython/core/prompts.py
IPython/core/pylabtools.py
IPython/core/release.py
IPython/core/shellapp.py
IPython/core/splitinput.py
IPython/core/ultratb.py
IPython/core/usage.py
IPython/core/magics/__init__.py
IPython/core/magics/ast_mod.py
IPython/core/magics/auto.py
IPython/core/magics/basic.py
IPython/core/magics/code.py
IPython/core/magics/config.py
IPython/core/magics/display.py
IPython/core/magics/execution.py
IPython/core/magics/extension.py
IPython/core/magics/history.py
IPython/core/magics/logging.py
IPython/core/magics/namespace.py
IPython/core/magics/osm.py
IPython/core/magics/packaging.py
IPython/core/magics/pylab.py
IPython/core/magics/script.py
IPython/core/profile/README_STARTUP
IPython/core/tests/2x2.jpg
ipython-8.29.0.dist-info/LICENSE
ipython-8.29.0.dist-info/METADATA
ipython-8.29.0.dist-info/WHEEL
ipython-8.29.0.dist-info/entry_points.txt
ipython-8.29.0.dist-info/top_level.txt
ipython-8.29.0.dist-info/RECORD
